<?xml version="1.0" encoding="utf-8"?>
<document xmlns="http://resources.qdexapps.com/schema/v1/QDocument.xsd" name="myDocument" id="GCEFB474D_015A_4C63_A1B2_5664F30B0077">

	<!-- Meta Data -->
	<metadata>
		<title>Lassonde Design Template</title>
		<creator>Sidique</creator>
		<coverImage src="resources/LassondeLogoDesign.png" />
		<abstract>This document is for testing purposes only. The material that is presented here should be treated as an example only.</abstract>
	</metadata>


  <include src="resources/curriculumStylesLassonde.xml" />
  <include src="resources/Utilities.xml" />
  <include src="resources/engine/JEngine.xml" />

  <!--                                      Header & Footer START                                         -->
  <header style="themeColour">
    <stack style="center" orientation="horizontal">
      <p></p>
    </stack>
  </header>
  <footer style="themeColour">
    <stack orientation="horizontal">
      <image style="tiny" src="resources/lassonde.png" inspect="false" />
      <p style="themeColourTitle">
        <style>
          <numbering suffix="true" counter="pages" />
          <textAlignment>center</textAlignment>
          <marginTop>30</marginTop>
          <foreground color="255 255 255" />
        </style>
      </p>
      <image style="tiny" src="resources/york.png" inspect="false" />
    </stack>
  </footer>
  <!--                                      Header & Footer END                                         -->



  <!-- Section 1 -->
  <!-- This is the standard way title pages are created. A great website to get copyright free images .. www.pexels.com
  *** The style: "pageLayout" is defined in curriculumStylesLassonde.xml. It simply sets the content to the center and adjusts the width to 80% ***-->
  <section name="section1" style="pageLayout">
    <title style="chapterTitle">1.1 Name of the Module</title>
    <p style="sectionHeading">Introduction</p>
    <image src="resources/spacex.jpg" />
    <stack orientation="vertical" style="contentBG">
      <p style="justifiedText">
        This is where your introductory content goes. This is a great place to introduce the concepts being discussed in the module and highlight
        some key terms in <b>bold</b>. Including a history of the topic or a high level view on the topic will be a great transition into the rest of the
        document. In some cases, explain the picture you've included to give a visual attachment to the document.
      </p>
    </stack>
  </section>


  <!--Make sure to set pageLayout to every section to keep consistency-->
	<sectionNoTitle name="section2" style="pageLayout">
		<p style="sectionHeading">Simple Page with Content</p>
		<stack orientation="vertical" name="contentStack" style="contentBG">
			<p>Here is where you can discuss content in detail, show examples and so on. To seperate paragraphs, it should be done with a new p tag like so:</p>
			<p>
				Lorem ipsum dolor sit amet, consectetur adipiscing elit, sed do eiusmod tempor incididunt ut labore et dolore magna aliqua. Ut enim ad minim veniam,
				quis nostrud exercitation ullamco laboris nisi ut aliquip ex ea commodo consequat. Duis aute irure dolor in reprehenderit in voluptate velit esse cillum
				dolore eu fugiat nulla pariatur. Excepteur sint occaecat cupidatat non proident, sunt in culpa qui officia deserunt mollit anim id est laborum.
			</p>
			<p><b>Add style "justifiedText" to the p tag with long sentence.</b></p>
			<p style="justifiedText">
				Lorem ipsum dolor sit amet, consectetur adipiscing elit, sed do eiusmod tempor incididunt ut labore et dolore magna aliqua. Ut enim ad minim veniam,
				quis nostrud exercitation ullamco laboris nisi ut aliquip ex ea commodo consequat. Duis aute irure dolor in reprehenderit in voluptate velit esse cillum
				dolore eu fugiat nulla pariatur. Excepteur sint occaecat cupidatat non proident, sunt in culpa qui officia deserunt mollit anim id est laborum.
			</p>
			<p><b>Centre the text uses style: "centeredText"</b></p>
			<p style="centeredText"><image xmlns="http://resources.qdexapps.com/schema/v1/QDocument.xsd" src="Equations/2fee03d7c812427cbe8f6dd549971711.png" alt="y=5x^2-4x+11" scale="0.0175" baseline="0" inspect="true" /></p>
			<p>To add media such as images or videos, keep it inside the stack.</p>
			<image src="resources/spacex2.jpg" />
		</stack>
		<p style="sectionHeading">Additional Topic</p>
		<stack orientation="vertical" name="contentStack2" style="contentBG">
			<p>
				If you would like to introduce another topic on the same page, simply follow the same styles as in the first topic. Make sure to create a seperate
				stack so that the sections can be easily identified. There is a margin of 20 that the section headings have so it already spaces out the different topics.
			</p>
		</stack>
	</sectionNoTitle>

	<!--TABULAR LAYOUT-->
	<sectionNoTitle style="pageLayout">
    <script>
      local tabsManager = TabsManager:new({tStack=tabs, cStack=contents, selectedTabIndex=1, numOfTabs=4})
      tabsManager:initStyle()
    </script>
		<p style="sectionHeading">Tabular Page Layout</p>
		<!--This stack only contains the tabs themselves and not the content. The content is held in a stack directly underneat the tabs.-->
    <stack name="tabs" orientation="horizontal" style="contentBG2">
      <stack style="contentBG">
        <button content="First Tab" style="tab">
          <onClick>
            tabsManager:changeTab(1)
          </onClick>
        </button>
      </stack>
      <stack style="contentBG">
        <button content="Second Tab" style="tab">
          <onClick>
            tabsManager:changeTab(2)
          </onClick>
        </button>
      </stack>
      <stack style="contentBG">
        <button content="Third Tab" style="tab">
          <onClick>
            tabsManager:changeTab(3)
          </onClick>
        </button>
      </stack>
      <stack style="contentBG">
        <button content="Fourth Tab" style="tab">
          <onClick>
            tabsManager:changeTab(4)
          </onClick>
        </button>
      </stack>
    </stack>
		<stack name="contents" orientation="vertical" style="contentBG">
			<stack orientation="vertical">
				<!--ADD YOUR CONTENT HERE-->
				<p>In this section, feel free to add a sub section heading to categorize topics within the tab.</p>
				<p style="subSectionHeading">Topic 1</p>
				<p>
					Lorem ipsum dolor sit amet, consectetur adipiscing elit, sed do eiusmod tempor incididunt ut labore et dolore magna aliqua. Ut enim ad minim veniam,
					quis nostrud exercitation ullamco laboris nisi ut aliquip ex ea commodo consequat. Duis aute irure dolor in reprehenderit in voluptate velit esse cillum
					dolore eu fugiat nulla pariatur. Excepteur sint occaecat cupidatat non proident, sunt in culpa qui officia deserunt mollit anim id est laborum.
				</p>
				<p style="subSectionHeading">Topic 2</p>
				<p>Adding images to your tabbed content is also very effective.</p>
				<image src="resources/spacex3.png" />
			</stack>
			<stack orientation="vertical">
				<!--ADD YOUR CONTENT HERE-->
				<p style="subSectionHeading">Topic 1</p>
				<p>
					Sed ut perspiciatis unde omnis iste natus error sit voluptatem accusantium doloremque laudantium,
					totam rem aperiam, eaque ipsa quae ab illo inventore veritatis et quasi architecto beatae vitae dicta sunt explicabo.
					Nemo enim ipsam voluptatem quia voluptas sit aspernatur aut odit aut fugit, sed quia consequuntur magni dolores eos qui ratione
					voluptatem sequi nesciunt. Neque porro quisquam est, qui dolorem ipsum quia dolor sit amet, consectetur, adipisci velit, sed quia non
					numquam eius modi tempora incidunt ut labore et dolore magnam aliquam quaerat voluptatem. Ut enim ad minima veniam, quis nostrum exercitationem
					ullam corporis suscipit laboriosam, nisi ut aliquid ex ea commodi consequatur? Quis autem vel eum iure reprehenderit qui in ea voluptate velit
					esse quam nihil molestiae consequatur, vel illum qui dolorem eum fugiat quo voluptas nulla pariatur?
				</p>
				<p style="subSectionHeading">Topic 2</p>
				<p>Adding images to your tabbed content is also very effective.</p>
				<image src="resources/spacex4.jpg" />
			</stack>
      <stack orientation="vertical">
        <!--ADD YOUR CONTENT HERE-->
				<p style="subSectionHeading">Topic 1</p>
				<p>
					At vero eos et accusamus et iusto odio dignissimos ducimus qui blanditiis praesentium voluptatum deleniti
					atque corrupti quos dolores et quas molestias excepturi sint occaecati cupiditate non provident, similique sunt in culpa
					qui officia deserunt mollitia animi, id est laborum et dolorum fuga. Et harum quidem rerum facilis est et expedita distinctio.
					Nam libero tempore, cum soluta nobis est eligendi optio cumque nihil impedit quo minus id quod maxime placeat facere possimus,
					omnis voluptas assumenda est, omnis dolor repellendus.
				</p>
				<p style="subSectionHeading">Topic 2</p>
				<p>Adding images to your tabbed content is also very effective.</p>
				<image src="resources/spacex5.jpg" />
			</stack>
      <stack orientation="vertical">
        <!--ADD YOUR CONTENT HERE-->
				<p style="subSectionHeading">Topic 1</p>
				<p>
					Temporibus autem quibusdam et aut officiis debitis aut rerum necessitatibus
					saepe eveniet ut et voluptates repudiandae sint et molestiae non recusandae.
					Itaque earum rerum hic tenetur a sapiente delectus, ut aut reiciendis voluptatibus
					maiores alias consequatur aut perferendis doloribus asperiores repellat.
				</p>
				<p style="subSectionHeading">Topic 2</p>
				<p>Adding images to your tabbed content is also very effective.</p>
				<image src="resources/spacex6.jpg" />
			</stack>
		</stack>
	</sectionNoTitle>

  
  
	<!--QUESTION STEP BY STEP LAYOUT-->
  <!--Setup StepsController with correct number of Steps-->
	<sectionNoTitle name="section4" style="pageLayout">
    <script>
      local stepsController = StepsController:new({stepsStack=stepsStack, numOfSteps=4})
    </script>
		<p style="sectionHeading">Question Step-by-Step</p>
		<stack orientation="vertical" style="contentBG">
			<p style="subSectionHeading">QUESTION 1</p>
			<p style="justifiedText">Here is where you ask the question... make sure to add an image that relates to the question to help visualize the question.</p>
			<image src="resources/diagram1.jpeg" />
		</stack>
    <stack name="stepsStack">
      <!--Each step is a stack, and each step has alternating background colors-->
      <stack orientation="horizontal">
        <stack name="stepStack" orientation="vertical">
          <p>Sketch a diagram</p>
          <stack name="cont" style="invisible">
            <!--CONTENT GOES HERE-->
            <p>This step is used to visualize the problem. Use the diagram given above as an example.</p>
          </stack>
        </stack>
        <button name="btn" style="stepByStepBtn">
          <onClick>
            stepsController:toggleStep(1)
          </onClick>
        </button>
      </stack>
      <stack orientation="horizontal">
        <stack name="stepStack" orientation="vertical">
          <p>Identify the variables</p>
          <stack name="cont" style="invisible">
            <stack orientation="horizontal">
              <stack orientation="vertical">
                <!--CONTENT GOES HERE-->
                <p>Make sure to include an explanation at each step and use latex to format your mathematical solutions!</p>
                <p>VARIABLES</p>
                <p><image xmlns="http://resources.qdexapps.com/schema/v1/QDocument.xsd" src="Equations/284dd57fb8f648c4ba0f093f4f420131.png" alt=" m = 100kg " scale="0.0175" baseline="0" inspect="true" /></p>
                <p><image xmlns="http://resources.qdexapps.com/schema/v1/QDocument.xsd" src="Equations/06e57804bc0b46a495cc9cb958838fe2.png" alt=" v_{i} = 0 \frac{m}{s} " scale="0.0175" baseline="0" inspect="true" /></p>
                <p><image xmlns="http://resources.qdexapps.com/schema/v1/QDocument.xsd" src="Equations/33afca138dfd48afbe18a3aa216db94d.png" alt=" v_{f} = ? \frac{m}{s} " scale="0.0175" baseline="0" inspect="true" /></p>
                <p><image xmlns="http://resources.qdexapps.com/schema/v1/QDocument.xsd" src="Equations/f3d8fa32e85647809935cb6acedbd272.png" alt=" h_{i} = 25 m " scale="0.0175" baseline="0" inspect="true" /></p>
                <p><image xmlns="http://resources.qdexapps.com/schema/v1/QDocument.xsd" src="Equations/097e018b3c7346e7ae6e5978b9a246d9.png" alt=" h_{f} = 3 m " scale="0.0175" baseline="0" inspect="true" /></p>
                <p><image xmlns="http://resources.qdexapps.com/schema/v1/QDocument.xsd" src="Equations/ce64a1047e4c4588a1da4091288160d4.png" alt=" g = 9.8 \frac{m}{s^2} " scale="0.0175" baseline="0" inspect="true" /></p>
              </stack>
            </stack>
          </stack>
        </stack>
        <button name="btn" style="stepByStepBtn">
          <onClick>
            stepsController:toggleStep(2)
          </onClick>
        </button>
      </stack>
      <stack orientation="horizontal">
        <stack name="stepStack" orientation="vertical">
          <!--CONTENT GOES HERE-->
          <p>Solve for potential energy at A</p>
          <stack name="cont" style="invisible">
            <p><image xmlns="http://resources.qdexapps.com/schema/v1/QDocument.xsd" src="Equations/1026528bab034d298e0259f44786a5fe.png" alt=" T_{E} = \frac{1}{2}mv^2 + mgh " scale="0.0175" baseline="0" inspect="true" /></p>
            <p><image xmlns="http://resources.qdexapps.com/schema/v1/QDocument.xsd" src="Equations/56eb3f3c227e4d4fadbceb5c44a4d8df.png" alt=" T_{E} = mgh " scale="0.0175" baseline="0" inspect="true" /></p>
            <p><image xmlns="http://resources.qdexapps.com/schema/v1/QDocument.xsd" src="Equations/3e2011fa95fe4e3da174c2f6fe5bbf2d.png" alt=" T_{E} = (100)(9.8)(25) " scale="0.0175" baseline="0" inspect="true" /></p>
            <p><image xmlns="http://resources.qdexapps.com/schema/v1/QDocument.xsd" src="Equations/e9cfa80a5c314caa93636334e45865f5.png" alt=" T_{E} = 2.45x10^4 J " scale="0.0175" baseline="0" inspect="true" /></p>
          </stack>
        </stack>
        <button name="btn" style="stepByStepBtn">
          <onClick>
            stepsController:toggleStep(3)
          </onClick>
        </button>
      </stack>
      <stack orientation="horizontal">
        <stack name="stepStack" orientation="vertical">
          <!--CONTENT GOES HERE-->
          <p>Solve for final speed at B</p>
          <stack name="cont" style="invisible">
            <p><image xmlns="http://resources.qdexapps.com/schema/v1/QDocument.xsd" src="Equations/1026528bab034d298e0259f44786a5fe.png" alt=" T_{E} = \frac{1}{2}mv^2 + mgh " scale="0.0175" baseline="0" inspect="true" /></p>
            <p><image xmlns="http://resources.qdexapps.com/schema/v1/QDocument.xsd" src="Equations/ff2f04e7280b498c9df0eaf88aa52802.png" alt=" 2.45x10^4 = \frac{1}{2}mv^2 + 0 " scale="0.0175" baseline="0" inspect="true" /></p>
            <p><image xmlns="http://resources.qdexapps.com/schema/v1/QDocument.xsd" src="Equations/7beb2181dda64427bef84dec40c7aa87.png" alt=" 4.9x10^4 = mv^2 + 0 " scale="0.0175" baseline="0" inspect="true" /></p>
            <p><image xmlns="http://resources.qdexapps.com/schema/v1/QDocument.xsd" src="Equations/ed0247daa1684c579bf2f939e9cb9e87.png" alt=" 490 = v^2 + 0 " scale="0.0175" baseline="0" inspect="true" /></p>
            <p><image xmlns="http://resources.qdexapps.com/schema/v1/QDocument.xsd" src="Equations/84f2899c0f4c476791bc1e20eb972019.png" alt=" \sqrt{490} = 22.14 \frac{m}{s} " scale="0.0175" baseline="0" inspect="true" /></p>
          </stack>
        </stack>
        <button name="btn" style="stepByStepBtn">
          <onClick>
            stepsController:toggleStep(4)
          </onClick>
        </button>
      </stack>
    </stack>
	</sectionNoTitle>

	<sectionNoTitle name="section5" style="pageLayout">    
		<p style="sectionHeading">Multiple Choice Single Page</p>
		<stack name="mcStack" style="mcStackLayout">
      <script>
        local mcController = MCController:new({choiceBtns={choicesTable:Child(2):Child(1).btn, choicesTable:Child(2):Child(2).btn, choicesTable:Child(4):Child(1).btn, choicesTable:Child(4):Child(2).btn}, checkBtn=checkBtn, answer=1})
      </script>
			<p style="subSectionHeading">Question 1</p>
			<table widths="10% 90%" grid="false">
				<row>
					<column>
						<image src="resources/question.png" inspect="false" />
					</column>
					<column>
						<p style="justifiedText">A rightward force is applied to a book in order to move it across a desk at constant velocity. Consider frictional forces. Neglect air resistance. What does the free body diagram of the book look like?</p>
					</column>
				</row>
			</table>
			<table name="choicesTable" grid="false" widths="50% 50%">
				<row>
					<column>
						<image src="resources/q.jpeg">
							<style>
								<widthPercentage>0.6</widthPercentage>
								<horizontalAlignment>center</horizontalAlignment>
							</style>
						</image>
					</column>
					<column>
						<image src="resources/q.jpeg">
							<style>
								<widthPercentage>0.6</widthPercentage>
								<horizontalAlignment>center</horizontalAlignment>
							</style>
						</image>
					</column>
				</row>
				<row>
					<column>
						<button name="btn" content="A" style="btnUnselected">
							<onClick>
                mcController:select(1)
							</onClick>
						</button>
					</column>
					<column>
						<button name="btn" content="B" style="btnUnselected">
							<onClick>
                mcController:select(2)
              </onClick>
						</button>
					</column>
				</row>
				<row>
					<column>
						<image src="resources/q.jpeg">
							<style>
								<widthPercentage>0.6</widthPercentage>
								<horizontalAlignment>center</horizontalAlignment>
							</style>
						</image>
					</column>
					<column>
						<image src="resources/q.jpeg">
							<style>
								<widthPercentage>0.6</widthPercentage>
								<horizontalAlignment>center</horizontalAlignment>
							</style>
						</image>
					</column>
				</row>
				<row>
					<column>
						<button name="btn" content="C" style="btnUnselected">
							<onClick>
                mcController:select(3)
              </onClick>
						</button>
					</column>
					<column>
						<button name="btn" content="D" style="btnUnselected">
							<onClick>
                mcController:select(4)
              </onClick>
						</button>
					</column>
				</row>
			</table>
			<button name="checkBtn" content="Check Answer">
				<onClick>
          mcController:checkAnswer()
        </onClick>
			</button>
		</stack>

  </sectionNoTitle>

	<sectionNoTitle name="section6" style="pageLayout">
    <script>
      local mqController = MQController:new({mqStack=mqStack, numOfSteps=2})
    </script>
		<p style="sectionHeading">Multiple Choice Nested</p>
		<stack orientation="vertical" style="contentBG">
			<p style="subSectionHeading">QUESTION 1</p>
			<p>Here is where you ask the question... make sure to add an image that relates to the question to help visualize the question.</p>
			<image src="resources/diagram1.jpeg" />
		</stack>
		<!--mqStack contains all the parts of the question. Don't change the inner tag names.
    copy & paste any one of the part to extend more parts if necessary.-->
    <stack name="mqStack" orientation="vertical">
      <stack orientation="vertical">
        <stack name="header" orientation="horizontal">
          <!--Step Title and Button-->
          <p name="title">PART A</p>
          <button name="btn" content="Show Part A" style="stepByStepBtn">
            <onClick>
              mqController:toggleStep(1)
            </onClick>
          </button>
        </stack>
        <stack name="content" style="invisible">
          <!--Step Content-->
          <stack>
            <script>
              local answer = 1
              local mcController = MCController:new({choiceBtns={choicesTable:Child(2):Child(1).btn, choicesTable:Child(2):Child(2).btn, choicesTable:Child(4):Child(1).btn, choicesTable:Child(4):Child(2).btn}, checkBtn=checkBtn, answer=answer})
            </script>
            <table widths="10% 90%" grid="false">
              <row>
                <column>
                  <image src="resources/question.png" inspect="false" />
                </column>
                <column>
                  <p style="justifiedText">A rightward force is applied to a book in order to move it across a desk at constant velocity. Consider frictional forces. Neglect air resistance. What does the free body diagram of the book look like?</p>
                </column>
              </row>
            </table>
            <table name="choicesTable" grid="false" widths="50% 50%">
              <row>
                <column>
                  <image src="resources/q.jpeg" style="mcLayout" />
                </column>
                <column>
                  <image src="resources/q.jpeg" style="mcLayout" />
                </column>
              </row>
              <row>
                <column>
                  <button name="btn" content="A" style="btnUnselected">
                    <onClick>
                      mcController:select(1)
                    </onClick>
                  </button>
                </column>
                <column>
                  <button name="btn" content="B" style="btnUnselected">
                    <onClick>
                      mcController:select(2)
                    </onClick>
                  </button>
                </column>
              </row>
              <row>
                <column>
                  <image src="resources/q.jpeg" style="mcLayout" />
                </column>
                <column>
                  <image src="resources/q.jpeg" style="mcLayout" />
                </column>
              </row>
              <row>
                <column>
                  <button name="btn" content="C" style="btnUnselected">
                    <onClick>
                      mcController:select(3)
                    </onClick>
                  </button>
                </column>
                <column>
                  <button name="btn" content="D" style="btnUnselected">
                    <onClick>
                      mcController:select(4)
                    </onClick>
                  </button>
                </column>
              </row>
            </table>
            <button name="checkBtn" content="Check Answer">
              <onClick>
                mcController:checkAnswer()
              </onClick>
            </button>
          </stack>
        </stack>
      </stack>
      <stack orientation="vertical">
        <stack name="header" orientation="horizontal">
          <!--Step Title and Button-->
          <p name="title">PART B</p>
          <button name="btn" content="Show Part B" style="stepByStepBtn">
            <onClick>
              mqController:toggleStep(2)
            </onClick>
          </button>
        </stack>
        <stack name="content" style="invisible">
          <!--Step Content-->
          <stack>
            <script>
              local answer = 1
              local mcController = MCController:new({choiceBtns={choicesTable:Child(2):Child(1).btn, choicesTable:Child(2):Child(2).btn, choicesTable:Child(4):Child(1).btn, choicesTable:Child(4):Child(2).btn}, checkBtn=checkBtn, answer=answer})
            </script>
            <table widths="10% 90%" grid="false">
              <row>
                <column>
                  <image src="resources/question.png" inspect="false" />
                </column>
                <column>
                  <p style="justifiedText">A rightward force is applied to a book in order to move it across a desk at constant velocity. Consider frictional forces. Neglect air resistance. What does the free body diagram of the book look like?</p>
                </column>
              </row>
            </table>
            <table name="choicesTable" grid="false" widths="50% 50%">
              <row>
                <column>
                  <image src="resources/q.jpeg" style="mcLayout" />
                </column>
                <column>
                  <image src="resources/q.jpeg" style="mcLayout" />
                </column>
              </row>
              <row>
                <column>
                  <button name="btn" content="A" style="btnUnselected">
                    <onClick>
                      mcController:select(1)
                    </onClick>
                  </button>
                </column>
                <column>
                  <button name="btn" content="B" style="btnUnselected">
                    <onClick>
                      mcController:select(2)
                    </onClick>
                  </button>
                </column>
              </row>
              <row>
                <column>
                  <image src="resources/q.jpeg" style="mcLayout" />
                </column>
                <column>
                  <image src="resources/q.jpeg" style="mcLayout" />
                </column>
              </row>
              <row>
                <column>
                  <button name="btn" content="C" style="btnUnselected">
                    <onClick>
                      mcController:select(3)
                    </onClick>
                  </button>
                </column>
                <column>
                  <button name="btn" content="D" style="btnUnselected">
                    <onClick>
                      mcController:select(4)
                    </onClick>
                  </button>
                </column>
              </row>
            </table>
            <button name="checkBtn" content="Check Answer">
              <onClick>
                mcController:checkAnswer()
              </onClick>
            </button>
          </stack>
        </stack>
      </stack>
    </stack>
    
	</sectionNoTitle>

  <sectionNoTitle style="pageLayout">
    <p style="sectionHeading">Simulation</p>
    <stack style="mcStackLayout">
      <p style="subSectionHeading">Drag the cloth and observe the changes (Replace with your Simulation Introduction/Description here)</p>
      <script>
        local world
      </script>
      <xyPlot name="plot" pan="custom" zoom="disabled">
        <onPan>
          <![CDATA[
          local mouseX = state.Current.X * world.width
          local mouseY = state.Current.Y * world.height
          world:mouseDidPress(mouseX,mouseY)
          ]]>
        </onPan>
        <axis name="XAxis" auto="fixed" dim="x" min="0" max="400" />
        <axis name="YAxis" auto="fixed" dim="y" min="0" max="300" />
        <series name="points" capacity="200" manual="true" draw="points" visible="false" />
        <series name="links" capacity="740" manual="true" draw="lineSegments" />
      </xyPlot>
      <simulation name="sim" period="0.016">
        <onUpdate>
          <![CDATA[
  world:draw()
  --plot.points:Update()
  plot.links:Update()
          ]]>
        </onUpdate>
      </simulation>
      <script>
        <![CDATA[
  world = World:new({sim=sim, plot=plot})
  world:createCurtain(plot.points, plot.links, 20, 10, 6, 140, 280)
  world:draw()
  --plot.points:Update()
  plot.links:Update()
        ]]>
      </script>
      <button name="btn" content="Start Simulation">
        <onClick>
          <![CDATA[
  if btn.Text == "Start Simulation" then
    btn.Text = "Pause Simulation"
    sim:Play()
  else
    btn.Text = "Start Simulation"
    sim:Pause()
  end
          ]]>
        </onClick>
      </button>
    </stack>
  </sectionNoTitle>

</document>